AndroidKaifaRumenjiaochengCYuyanBianchengWang/README.md
AndroidKaifaRumenjiaochengCYuyanBianchengWang/__init__.py
AndroidKaifaRumenjiaochengCYuyanBianchengWang/__main__.py
AndroidKaifaRumenjiaochengCYuyanBianchengWang/file.epub
AndroidKaifaRumenjiaochengCYuyanBianchengWang/index.html
AndroidKaifaRumenjiaochengCYuyanBianchengWang/css/__init__.py
AndroidKaifaRumenjiaochengCYuyanBianchengWang/css/annotations.css
AndroidKaifaRumenjiaochengCYuyanBianchengWang/css/main.css
AndroidKaifaRumenjiaochengCYuyanBianchengWang/css/normalize.css
AndroidKaifaRumenjiaochengCYuyanBianchengWang/css/popup.css
AndroidKaifaRumenjiaochengCYuyanBianchengWang/font/__init__.py
AndroidKaifaRumenjiaochengCYuyanBianchengWang/font/fontello.eot
AndroidKaifaRumenjiaochengCYuyanBianchengWang/font/fontello.svg
AndroidKaifaRumenjiaochengCYuyanBianchengWang/font/fontello.ttf
AndroidKaifaRumenjiaochengCYuyanBianchengWang/font/fontello.woff
AndroidKaifaRumenjiaochengCYuyanBianchengWang/img/__init__.py
AndroidKaifaRumenjiaochengCYuyanBianchengWang/img/annotator-glyph-sprite.png
AndroidKaifaRumenjiaochengCYuyanBianchengWang/img/annotator-icon-sprite.png
AndroidKaifaRumenjiaochengCYuyanBianchengWang/img/apple-touch-icon.png
AndroidKaifaRumenjiaochengCYuyanBianchengWang/img/cancelfullscreen.png
AndroidKaifaRumenjiaochengCYuyanBianchengWang/img/close.png
AndroidKaifaRumenjiaochengCYuyanBianchengWang/img/fullscreen.png
AndroidKaifaRumenjiaochengCYuyanBianchengWang/img/loader.gif
AndroidKaifaRumenjiaochengCYuyanBianchengWang/img/menu-icon.png
AndroidKaifaRumenjiaochengCYuyanBianchengWang/img/save.png
AndroidKaifaRumenjiaochengCYuyanBianchengWang/img/saved.png
AndroidKaifaRumenjiaochengCYuyanBianchengWang/img/settings-s.png
AndroidKaifaRumenjiaochengCYuyanBianchengWang/img/settings.png
AndroidKaifaRumenjiaochengCYuyanBianchengWang/img/star.png
AndroidKaifaRumenjiaochengCYuyanBianchengWang/js/__init__.py
AndroidKaifaRumenjiaochengCYuyanBianchengWang/js/epub.js
android_kaifa_rumenjiaocheng_c_yuyan_biancheng_wang-2024.3.4.0.dist-info/METADATA
android_kaifa_rumenjiaocheng_c_yuyan_biancheng_wang-2024.3.4.0.dist-info/WHEEL
android_kaifa_rumenjiaocheng_c_yuyan_biancheng_wang-2024.3.4.0.dist-info/entry_points.txt
android_kaifa_rumenjiaocheng_c_yuyan_biancheng_wang-2024.3.4.0.dist-info/top_level.txt
android_kaifa_rumenjiaocheng_c_yuyan_biancheng_wang-2024.3.4.0.dist-info/RECORD
